terminological_ontological_coverage/SmartStoplist.txt
terminological_ontological_coverage/__init__.py
terminological_ontological_coverage/keyword_comparison.py
tests/__init__.py
tests/test-cli.py
tests/test-package.py
terminological_ontological_coverage-1.0.1.dist-info/METADATA
terminological_ontological_coverage-1.0.1.dist-info/WHEEL
terminological_ontological_coverage-1.0.1.dist-info/entry_points.txt
terminological_ontological_coverage-1.0.1.dist-info/top_level.txt
terminological_ontological_coverage-1.0.1.dist-info/RECORD
