Metadata-Version: 2.1
Name: terminological_ontological_coverage
Version: 1.0.1
Summary: A package for keyword and ontology comparison.
Author: Anna Sofia Lippolis
Keywords: keywords ontology comparison
Classifier: Programming Language :: Python :: 3
Classifier: License :: OSI Approved :: MIT License
Classifier: Operating System :: OS Independent
Requires-Dist: PyMuPDF
Requires-Dist: rdflib
Requires-Dist: rake-nltk
Requires-Dist: keybert
Requires-Dist: pandas
Requires-Dist: argparse
Requires-Dist: transformers
